pyrot/__init__.py
pyrot/config.py
pyrot/logging.py
pyrot/ro_interface.py
pyrot/eye_modelling/__init__.py
pyrot/eye_modelling/clipbased_model.py
pyrot/eye_modelling/common_methods.py
pyrot/eye_modelling/ellipsoid_fit.py
pyrot/eye_modelling/match_sclera_to_markers.py
pyrot/eye_modelling/match_with_biometry.py
pyrot/eye_modelling/datamodels/__init__.py
pyrot/eye_modelling/datamodels/export.py
pyrot/eye_modelling/datamodels/models.py
pyrot/eye_modelling/datamodels/validators.py
rayocular_toolbox-1.0.0b1.dist-info/METADATA
rayocular_toolbox-1.0.0b1.dist-info/WHEEL
rayocular_toolbox-1.0.0b1.dist-info/licenses/LICENSE
rayocular_toolbox-1.0.0b1.dist-info/RECORD
