Metadata-Version: 2.4
Name: rayocular-toolbox
Version: 1.0.0b1
Summary: A Python toolbox for ocular proton therapy planning in RayOcular
Author: Jan-Willem Beenakker, Lennart Pors, Corné Haasjes
Maintainer-email: MReye research group <pyrot@mreye.nl>
License: MIT License
License-File: LICENSE
Keywords: Proton therapy,RayOcular,RayStation
Classifier: Development Status :: 1 - Planning
Classifier: Programming Language :: Python :: 3
Requires-Python: <3.9,>=3.6
Requires-Dist: numpy
Requires-Dist: pythonnet>=2.5.2
